[
{"Thread":"Main","Number":"13001"},
{"Thread":"Main","Number":"13002"},
{"Thread":"Main","Number":"13003"},
{"Thread":"Main","Number":"13004"},
{"Thread":"Main","Number":"13005"},
{"Thread":"Main","Number":"13006"},
{"Thread":"Main","Number":"13007"},
{"Thread":"Main","Number":"13008"},
{"Thread":"Main","Number":"13009"},
{"Thread":"Main","Number":"13010"},
{"Thread":"Main","Number":"13011"},
{"Thread":"Main","Number":"13012"},
{"Thread":"Main","Number":"13013"},
{"Thread":"Main","Number":"13014"},
{"Thread":"Main","Number":"13015"},
{"Thread":"Main","Number":"13016"},
{"Thread":"Main","Number":"13017"},
{"Thread":"Main","Number":"13018"},
{"Thread":"Main","Number":"13019"},
{"Thread":"Main","Number":"13020"},
{"Thread":"Main","Number":"13021"},
{"Thread":"Main","Number":"13022"},
{"Thread":"Main","Number":"13023"},
{"Thread":"Main","Number":"13024"},
{"Thread":"Main","Number":"13025"},
{"Thread":"Main","Number":"13026"},
{"Thread":"Main","Number":"13027"},
{"Thread":"Main","Number":"13028"},
{"Thread":"Main","Number":"13029"},
{"Thread":"Main","Number":"13030"},
{"Thread":"Main","Number":"13031"},
{"Thread":"Main","Number":"13032"},
{"Thread":"Main","Number":"13033"},
{"Thread":"Main","Number":"13034"},
{"Thread":"Main","Number":"13035"},
{"Thread":"Main","Number":"13036"},
{"Thread":"Main","Number":"13037"},
{"Thread":"Main","Number":"13038"},
{"Thread":"Main","Number":"13039"},
{"Thread":"Main","Number":"13040"},
{"Thread":"Main","Number":"13041"},
{"Thread":"Main","Number":"13042"},
{"Thread":"Main","Number":"13043"},
{"Thread":"Main","Number":"13044"},
{"Thread":"Main","Number":"13045"},
{"Thread":"Main","Number":"13046"},
{"Thread":"Main","Number":"13047"},
{"Thread":"Main","Number":"13048"},
{"Thread":"Main","Number":"13049"},
{"Thread":"Main","Number":"13050"},
{"Thread":"Main","Number":"13051"},
{"Thread":"Main","Number":"13052"},
{"Thread":"Main","Number":"13053"},
{"Thread":"Main","Number":"13054"},
{"Thread":"Main","Number":"13055"},
{"Thread":"Main","Number":"13056"},
{"Thread":"Main","Number":"13057"},
{"Thread":"Main","Number":"13058"},
{"Thread":"Main","Number":"13059"},
{"Thread":"Main","Number":"13060"},
{"Thread":"Main","Number":"13061"},
{"Thread":"Main","Number":"13062"},
{"Thread":"Main","Number":"13063"},
{"Thread":"Main","Number":"13064"},
{"Thread":"Main","Number":"13065"},
{"Thread":"Main","Number":"13066"},
{"Thread":"Main","Number":"13067"},
{"Thread":"Main","Number":"13068"},
{"Thread":"Main","Number":"13069"},
{"Thread":"Main","Number":"13070"},
{"Thread":"Main","Number":"13071"},
{"Thread":"Main","Number":"13072"},
{"Thread":"Main","Number":"13073"},
{"Thread":"Main","Number":"13074"},
{"Thread":"Main","Number":"13075"},
{"Thread":"Main","Number":"13076"},
{"Thread":"Main","Number":"13077"},
{"Thread":"Main","Number":"13078"},
{"Thread":"Main","Number":"13079"},
{"Thread":"Main","Number":"13080"},
{"Thread":"Main","Number":"13081"},
{"Thread":"Main","Number":"13082"},
{"Thread":"Main","Number":"13083"},
{"Thread":"Main","Number":"13084"},
{"Thread":"Main","Number":"13085"},
{"Thread":"Main","Number":"13086"},
{"Thread":"Main","Number":"13087"},
{"Thread":"Main","Number":"13088"},
{"Thread":"Main","Number":"13089"},
{"Thread":"Main","Number":"13090"},
{"Thread":"Main","Number":"13091"},
{"Thread":"Main","Number":"13092"},
{"Thread":"Main","Number":"13093"},
{"Thread":"Main","Number":"13094"},
{"Thread":"Main","Number":"13095"},
{"Thread":"Main","Number":"13096"},
{"Thread":"Main","Number":"13097"},
{"Thread":"Main","Number":"13098"},
{"Thread":"Main","Number":"13099"},
{"Thread":"Main","Number":"13100"},
{"Thread":"Main","Number":"13101"},
{"Thread":"Main","Number":"13102"},
{"Thread":"Main","Number":"13103"},
{"Thread":"Main","Number":"13104"},
{"Thread":"Main","Number":"13105"},
{"Thread":"Main","Number":"13106"},
{"Thread":"Main","Number":"13107"},
{"Thread":"Main","Number":"13108"},
{"Thread":"Main","Number":"13109"},
{"Thread":"Main","Number":"13110"},
{"Thread":"Main","Number":"13111"},
{"Thread":"Main","Number":"13112"},
{"Thread":"Main","Number":"13113"},
{"Thread":"Main","Number":"13114"},
{"Thread":"Main","Number":"13115"},
{"Thread":"Main","Number":"13116"},
{"Thread":"Main","Number":"13117"},
{"Thread":"Main","Number":"13118"},
{"Thread":"Main","Number":"13119"},
{"Thread":"Main","Number":"13120"},
{"Thread":"Main","Number":"13121"},
{"Thread":"Main","Number":"13122"},
{"Thread":"Main","Number":"13123"},
{"Thread":"Main","Number":"13124"},
{"Thread":"Main","Number":"13125"},
{"Thread":"Main","Number":"13126"},
{"Thread":"Main","Number":"13127"},
{"Thread":"Main","Number":"13128"},
{"Thread":"Main","Number":"13129"},
{"Thread":"Main","Number":"13130"},
{"Thread":"Main","Number":"13131"},
{"Thread":"Main","Number":"13132"},
{"Thread":"Main","Number":"13133"},
{"Thread":"Main","Number":"13134"},
{"Thread":"Main","Number":"13135"},
{"Thread":"Main","Number":"13136"},
{"Thread":"Main","Number":"13137"},
{"Thread":"Main","Number":"13138"},
{"Thread":"Main","Number":"13139"},
{"Thread":"Main","Number":"13140"},
{"Thread":"Main","Number":"13141"},
{"Thread":"Main","Number":"13142"},
{"Thread":"Main","Number":"13143"},
{"Thread":"Main","Number":"13144"},
{"Thread":"Main","Number":"13145"},
{"Thread":"Main","Number":"13146"},
{"Thread":"Main","Number":"13147"},
{"Thread":"Main","Number":"13148"},
{"Thread":"Main","Number":"13149"},
{"Thread":"Main","Number":"13150"},
{"Thread":"Main","Number":"13151"},
{"Thread":"Main","Number":"13152"},
{"Thread":"Main","Number":"13153"},
{"Thread":"Main","Number":"13154"},
{"Thread":"Main","Number":"13155"},
{"Thread":"Main","Number":"13156"},
{"Thread":"Main","Number":"13157"},
{"Thread":"Main","Number":"13158"},
{"Thread":"Main","Number":"13159"},
{"Thread":"Main","Number":"13160"},
{"Thread":"Main","Number":"13161"},
{"Thread":"Main","Number":"13162"},
{"Thread":"Main","Number":"13163"},
{"Thread":"Main","Number":"13164"},
{"Thread":"Main","Number":"13165"},
{"Thread":"Main","Number":"13166"},
{"Thread":"Main","Number":"13167"},
{"Thread":"Main","Number":"13168"},
{"Thread":"Main","Number":"13169"},
{"Thread":"Main","Number":"13170"},
{"Thread":"Main","Number":"13171"},
{"Thread":"Main","Number":"13172"},
{"Thread":"Main","Number":"13173"},
{"Thread":"Main","Number":"13174"},
{"Thread":"Main","Number":"13175"},
{"Thread":"Main","Number":"13176"},
{"Thread":"Main","Number":"13177"},
{"Thread":"Main","Number":"13178"},
{"Thread":"Main","Number":"13179"},
{"Thread":"Main","Number":"13180"},
{"Thread":"Main","Number":"13181"},
{"Thread":"Main","Number":"13182"},
{"Thread":"Main","Number":"13183"},
{"Thread":"Main","Number":"13184"},
{"Thread":"Main","Number":"13185"},
{"Thread":"Main","Number":"13186"},
{"Thread":"Main","Number":"13187"},
{"Thread":"Main","Number":"13188"},
{"Thread":"Main","Number":"13189"},
{"Thread":"Main","Number":"13190"},
{"Thread":"Main","Number":"13191"},
{"Thread":"Main","Number":"13192"},
{"Thread":"Main","Number":"13193"},
{"Thread":"Main","Number":"13194"},
{"Thread":"Main","Number":"13195"},
{"Thread":"Main","Number":"13196"},
{"Thread":"Main","Number":"13197"},
{"Thread":"Main","Number":"13198"},
{"Thread":"Main","Number":"13199"},
{"Thread":"Main","Number":"13200"},
{"Thread":"Main","Number":"13201"},
{"Thread":"Main","Number":"13202"},
{"Thread":"Main","Number":"13203"},
{"Thread":"Main","Number":"13204"},
{"Thread":"Main","Number":"13205"},
{"Thread":"Main","Number":"13206"},
{"Thread":"Main","Number":"13207"},
{"Thread":"Main","Number":"13208"},
{"Thread":"Main","Number":"13209"},
{"Thread":"Main","Number":"13210"},
{"Thread":"Main","Number":"13211"},
{"Thread":"Main","Number":"13212"},
{"Thread":"Main","Number":"13213"},
{"Thread":"Main","Number":"13214"},
{"Thread":"Main","Number":"13215"},
{"Thread":"Main","Number":"13216"},
{"Thread":"Main","Number":"13217"},
{"Thread":"Main","Number":"13218"},
{"Thread":"Main","Number":"13219"},
{"Thread":"Main","Number":"13220"},
{"Thread":"Main","Number":"13221"},
{"Thread":"Main","Number":"13222"},
{"Thread":"Main","Number":"13223"},
{"Thread":"Main","Number":"13224"},
{"Thread":"Main","Number":"13225"},
{"Thread":"Main","Number":"13226"},
{"Thread":"Main","Number":"13227"},
{"Thread":"Main","Number":"13228"},
{"Thread":"Main","Number":"13229"},
{"Thread":"Main","Number":"13230"},
{"Thread":"Main","Number":"13231"},
{"Thread":"Main","Number":"13232"},
{"Thread":"Main","Number":"13233"},
{"Thread":"Main","Number":"13234"},
{"Thread":"Main","Number":"13235"},
{"Thread":"Main","Number":"13236"},
{"Thread":"Main","Number":"13237"},
{"Thread":"Main","Number":"13238"},
{"Thread":"Main","Number":"13239"},
{"Thread":"Main","Number":"13240"},
{"Thread":"Main","Number":"13241"},
{"Thread":"Main","Number":"13242"},
{"Thread":"Main","Number":"13243"},
{"Thread":"Main","Number":"13244"},
{"Thread":"Main","Number":"13245"},
{"Thread":"Main","Number":"13246"},
{"Thread":"Main","Number":"13247"},
{"Thread":"Main","Number":"13248"},
{"Thread":"Main","Number":"13249"},
{"Thread":"Main","Number":"13250"},
{"Thread":"Main","Number":"13251"},
{"Thread":"Main","Number":"13252"},
{"Thread":"Main","Number":"13253"},
{"Thread":"Main","Number":"13254"},
{"Thread":"Main","Number":"13255"},
{"Thread":"Main","Number":"13256"},
{"Thread":"Main","Number":"13257"},
{"Thread":"Main","Number":"13258"},
{"Thread":"Main","Number":"13259"},
{"Thread":"Main","Number":"13260"},
{"Thread":"Main","Number":"13261"},
{"Thread":"Main","Number":"13262"},
{"Thread":"Main","Number":"13263"},
{"Thread":"Main","Number":"13264"},
{"Thread":"Main","Number":"13265"},
{"Thread":"Main","Number":"13266"},
{"Thread":"Main","Number":"13267"},
{"Thread":"Main","Number":"13268"},
{"Thread":"Main","Number":"13269"},
{"Thread":"Main","Number":"13270"},
{"Thread":"Main","Number":"13271"},
{"Thread":"Main","Number":"13272"},
{"Thread":"Main","Number":"13273"},
{"Thread":"Main","Number":"13274"},
{"Thread":"Main","Number":"13275"},
{"Thread":"Main","Number":"13276"},
{"Thread":"Main","Number":"13277"},
{"Thread":"Main","Number":"13278"},
{"Thread":"Main","Number":"13279"},
{"Thread":"Main","Number":"13280"},
{"Thread":"Main","Number":"13281"},
{"Thread":"Main","Number":"13282"},
{"Thread":"Main","Number":"13283"},
{"Thread":"Main","Number":"13284"},
{"Thread":"Main","Number":"13285"},
{"Thread":"Main","Number":"13286"},
{"Thread":"Main","Number":"13287"},
{"Thread":"Main","Number":"13288"},
{"Thread":"Main","Number":"13289"},
{"Thread":"Main","Number":"13290"},
{"Thread":"Main","Number":"13291"},
{"Thread":"Main","Number":"13292"},
{"Thread":"Main","Number":"13293"},
{"Thread":"Main","Number":"13294"},
{"Thread":"Main","Number":"13295"},
{"Thread":"Main","Number":"13296"},
{"Thread":"Main","Number":"13297"},
{"Thread":"Main","Number":"13298"},
{"Thread":"Main","Number":"13299"},
{"Thread":"Main","Number":"13300"},
{"Thread":"Main","Number":"13301"},
{"Thread":"Main","Number":"13302"},
{"Thread":"Main","Number":"13303"},
{"Thread":"Main","Number":"13304"},
{"Thread":"Main","Number":"13305"},
{"Thread":"Main","Number":"13306"},
{"Thread":"Main","Number":"13307"},
{"Thread":"Main","Number":"13308"},
{"Thread":"Main","Number":"13309"},
{"Thread":"Main","Number":"13310"},
{"Thread":"Main","Number":"13311"},
{"Thread":"Main","Number":"13312"},
{"Thread":"Main","Number":"13313"},
{"Thread":"Main","Number":"13314"},
{"Thread":"Main","Number":"13315"},
{"Thread":"Main","Number":"13316"},
{"Thread":"Main","Number":"13317"},
{"Thread":"Main","Number":"13318"},
{"Thread":"Main","Number":"13319"},
{"Thread":"Main","Number":"13320"},
{"Thread":"Main","Number":"13321"},
{"Thread":"Main","Number":"13322"},
{"Thread":"Main","Number":"13323"},
{"Thread":"Main","Number":"13324"},
{"Thread":"Main","Number":"13325"},
{"Thread":"Main","Number":"13326"},
{"Thread":"Main","Number":"13327"},
{"Thread":"Main","Number":"13328"},
{"Thread":"Main","Number":"13329"},
{"Thread":"Main","Number":"13330"},
{"Thread":"Main","Number":"13331"},
{"Thread":"Main","Number":"13332"},
{"Thread":"Main","Number":"13333"},
{"Thread":"Main","Number":"13334"},
{"Thread":"Main","Number":"13335"},
{"Thread":"Main","Number":"13336"},
{"Thread":"Main","Number":"13337"},
{"Thread":"Main","Number":"13338"},
{"Thread":"Main","Number":"13339"},
{"Thread":"Main","Number":"13340"},
{"Thread":"Main","Number":"13341"},
{"Thread":"Main","Number":"13342"},
{"Thread":"Main","Number":"13343"},
{"Thread":"Main","Number":"13344"},
{"Thread":"Main","Number":"13345"},
{"Thread":"Main","Number":"13346"},
{"Thread":"Main","Number":"13347"},
{"Thread":"Main","Number":"13348"},
{"Thread":"Main","Number":"13349"},
{"Thread":"Main","Number":"13350"},
{"Thread":"Main","Number":"13351"},
{"Thread":"Main","Number":"13352"},
{"Thread":"Main","Number":"13353"},
{"Thread":"Main","Number":"13354"},
{"Thread":"Main","Number":"13355"},
{"Thread":"Main","Number":"13356"},
{"Thread":"Main","Number":"13357"},
{"Thread":"Main","Number":"13358"},
{"Thread":"Main","Number":"13359"},
{"Thread":"Main","Number":"13360"},
{"Thread":"Main","Number":"13361"},
{"Thread":"Main","Number":"13362"},
{"Thread":"Main","Number":"13363"},
{"Thread":"Main","Number":"13364"},
{"Thread":"Main","Number":"13365"},
{"Thread":"Main","Number":"13366"},
{"Thread":"Main","Number":"13367"},
{"Thread":"Main","Number":"13368"},
{"Thread":"Main","Number":"13369"},
{"Thread":"Main","Number":"13370"},
{"Thread":"Main","Number":"13371"},
{"Thread":"Main","Number":"13372"},
{"Thread":"Main","Number":"13373"},
{"Thread":"Main","Number":"13374"},
{"Thread":"Main","Number":"13375"},
{"Thread":"Main","Number":"13376"},
{"Thread":"Main","Number":"13377"},
{"Thread":"Main","Number":"13378"},
{"Thread":"Main","Number":"13379"},
{"Thread":"Main","Number":"13380"},
{"Thread":"Main","Number":"13381"},
{"Thread":"Main","Number":"13382"},
{"Thread":"Main","Number":"13383"},
{"Thread":"Main","Number":"13384"},
{"Thread":"Main","Number":"13385"},
{"Thread":"Main","Number":"13386"},
{"Thread":"Main","Number":"13387"},
{"Thread":"Main","Number":"13388"},
{"Thread":"Main","Number":"13389"},
{"Thread":"Main","Number":"13390"},
{"Thread":"Main","Number":"13391"},
{"Thread":"Main","Number":"13392"},
{"Thread":"Main","Number":"13393"},
{"Thread":"Main","Number":"13394"},
{"Thread":"Main","Number":"13395"},
{"Thread":"Main","Number":"13396"},
{"Thread":"Main","Number":"13397"},
{"Thread":"Main","Number":"13398"},
{"Thread":"Main","Number":"13399"},
{"Thread":"Main","Number":"13400"},
{"Thread":"Main","Number":"13401"},
{"Thread":"Main","Number":"13402"},
{"Thread":"Main","Number":"13403"},
{"Thread":"Main","Number":"13404"},
{"Thread":"Main","Number":"13405"},
{"Thread":"Main","Number":"13406"},
{"Thread":"Main","Number":"13407"},
{"Thread":"Main","Number":"13408"},
{"Thread":"Main","Number":"13409"},
{"Thread":"Main","Number":"13410"},
{"Thread":"Main","Number":"13411"},
{"Thread":"Main","Number":"13412"},
{"Thread":"Main","Number":"13413"},
{"Thread":"Main","Number":"13414"},
{"Thread":"Main","Number":"13415"},
{"Thread":"Main","Number":"13416"},
{"Thread":"Main","Number":"13417"},
{"Thread":"Main","Number":"13418"},
{"Thread":"Main","Number":"13419"},
{"Thread":"Main","Number":"13420"},
{"Thread":"Main","Number":"13421"},
{"Thread":"Main","Number":"13422"},
{"Thread":"Main","Number":"13423"},
{"Thread":"Main","Number":"13424"},
{"Thread":"Main","Number":"13425"},
{"Thread":"Main","Number":"13426"},
{"Thread":"Main","Number":"13427"},
{"Thread":"Main","Number":"13428"},
{"Thread":"Main","Number":"13429"},
{"Thread":"Main","Number":"13430"},
{"Thread":"Main","Number":"13431"},
{"Thread":"Main","Number":"13432"},
{"Thread":"Main","Number":"13433"},
{"Thread":"Main","Number":"13434"},
{"Thread":"Main","Number":"13435"},
{"Thread":"Main","Number":"13436"},
{"Thread":"Main","Number":"13437"},
{"Thread":"Main","Number":"13438"},
{"Thread":"Main","Number":"13439"},
{"Thread":"Main","Number":"13440"},
{"Thread":"Main","Number":"13441"},
{"Thread":"Main","Number":"13442"},
{"Thread":"Main","Number":"13443"},
{"Thread":"Main","Number":"13444"},
{"Thread":"Main","Number":"13445"},
{"Thread":"Main","Number":"13446"},
{"Thread":"Main","Number":"13447"},
{"Thread":"Main","Number":"13448"},
{"Thread":"Main","Number":"13449"},
{"Thread":"Main","Number":"13450"},
{"Thread":"Main","Number":"13451"},
{"Thread":"Main","Number":"13452"},
{"Thread":"Main","Number":"13453"},
{"Thread":"Main","Number":"13454"},
{"Thread":"Main","Number":"13455"},
{"Thread":"Main","Number":"13456"},
{"Thread":"Main","Number":"13457"},
{"Thread":"Main","Number":"13458"},
{"Thread":"Main","Number":"13459"},
{"Thread":"Main","Number":"13460"},
{"Thread":"Main","Number":"13461"},
{"Thread":"Main","Number":"13462"},
{"Thread":"Main","Number":"13463"},
{"Thread":"Main","Number":"13464"},
{"Thread":"Main","Number":"13465"},
{"Thread":"Main","Number":"13466"},
{"Thread":"Main","Number":"13467"},
{"Thread":"Main","Number":"13468"},
{"Thread":"Main","Number":"13469"},
{"Thread":"Main","Number":"13470"},
{"Thread":"Main","Number":"13471"},
{"Thread":"Main","Number":"13472"},
{"Thread":"Main","Number":"13473"},
{"Thread":"Main","Number":"13474"},
{"Thread":"Main","Number":"13475"},
{"Thread":"Main","Number":"13476"},
{"Thread":"Main","Number":"13477"},
{"Thread":"Main","Number":"13478"},
{"Thread":"Main","Number":"13479"},
{"Thread":"Main","Number":"13480"},
{"Thread":"Main","Number":"13481"},
{"Thread":"Main","Number":"13482"},
{"Thread":"Main","Number":"13483"},
{"Thread":"Main","Number":"13484"},
{"Thread":"Main","Number":"13485"},
{"Thread":"Main","Number":"13486"},
{"Thread":"Main","Number":"13487"},
{"Thread":"Main","Number":"13488"},
{"Thread":"Main","Number":"13489"},
{"Thread":"Main","Number":"13490"},
{"Thread":"Main","Number":"13491"},
{"Thread":"Main","Number":"13492"},
{"Thread":"Main","Number":"13493"},
{"Thread":"Main","Number":"13494"},
{"Thread":"Main","Number":"13495"},
{"Thread":"Main","Number":"13496"},
{"Thread":"Main","Number":"13497"},
{"Thread":"Main","Number":"13498"},
{"Thread":"Main","Number":"13499"},
{"Thread":"Main","Number":"13500"},
{"Thread":"Main","Number":"13501"},
{"Thread":"Main","Number":"13502"},
{"Thread":"Main","Number":"13503"},
{"Thread":"Main","Number":"13504"},
{"Thread":"Main","Number":"13505"},
{"Thread":"Main","Number":"13506"},
{"Thread":"Main","Number":"13507"},
{"Thread":"Main","Number":"13508"},
{"Thread":"Main","Number":"13509"},
{"Thread":"Main","Number":"13510"},
{"Thread":"Main","Number":"13511"},
{"Thread":"Main","Number":"13512"},
{"Thread":"Main","Number":"13513"},
{"Thread":"Main","Number":"13514"},
{"Thread":"Main","Number":"13515"},
{"Thread":"Main","Number":"13516"},
{"Thread":"Main","Number":"13517"},
{"Thread":"Main","Number":"13518"},
{"Thread":"Main","Number":"13519"},
{"Thread":"Main","Number":"13520"},
{"Thread":"Main","Number":"13521"},
{"Thread":"Main","Number":"13522"},
{"Thread":"Main","Number":"13523"},
{"Thread":"Main","Number":"13524"},
{"Thread":"Main","Number":"13525"},
{"Thread":"Main","Number":"13526"},
{"Thread":"Main","Number":"13527"},
{"Thread":"Main","Number":"13528"},
{"Thread":"Main","Number":"13529"},
{"Thread":"Main","Number":"13530"},
{"Thread":"Main","Number":"13531"},
{"Thread":"Main","Number":"13532"},
{"Thread":"Main","Number":"13533"},
{"Thread":"Main","Number":"13534"},
{"Thread":"Main","Number":"13535"},
{"Thread":"Main","Number":"13536"},
{"Thread":"Main","Number":"13537"},
{"Thread":"Main","Number":"13538"},
{"Thread":"Main","Number":"13539"},
{"Thread":"Main","Number":"13540"},
{"Thread":"Main","Number":"13541"},
{"Thread":"Main","Number":"13542"},
{"Thread":"Main","Number":"13543"},
{"Thread":"Main","Number":"13544"},
{"Thread":"Main","Number":"13545"},
{"Thread":"Main","Number":"13546"},
{"Thread":"Main","Number":"13547"},
{"Thread":"Main","Number":"13548"},
{"Thread":"Main","Number":"13549"},
{"Thread":"Main","Number":"13550"},
{"Thread":"Main","Number":"13551"},
{"Thread":"Main","Number":"13552"},
{"Thread":"Main","Number":"13553"},
{"Thread":"Main","Number":"13554"},
{"Thread":"Main","Number":"13555"},
{"Thread":"Main","Number":"13556"},
{"Thread":"Main","Number":"13557"},
{"Thread":"Main","Number":"13558"},
{"Thread":"Main","Number":"13559"},
{"Thread":"Main","Number":"13560"},
{"Thread":"Main","Number":"13561"},
{"Thread":"Main","Number":"13562"},
{"Thread":"Main","Number":"13563"},
{"Thread":"Main","Number":"13564"},
{"Thread":"Main","Number":"13565"},
{"Thread":"Main","Number":"13566"},
{"Thread":"Main","Number":"13567"},
{"Thread":"Main","Number":"13568"},
{"Thread":"Main","Number":"13569"},
{"Thread":"Main","Number":"13570"},
{"Thread":"Main","Number":"13571"},
{"Thread":"Main","Number":"13572"},
{"Thread":"Main","Number":"13573"},
{"Thread":"Main","Number":"13574"},
{"Thread":"Main","Number":"13575"},
{"Thread":"Main","Number":"13576"},
{"Thread":"Main","Number":"13577"},
{"Thread":"Main","Number":"13578"},
{"Thread":"Main","Number":"13579"},
{"Thread":"Main","Number":"13580"},
{"Thread":"Main","Number":"13581"},
{"Thread":"Main","Number":"13582"},
{"Thread":"Main","Number":"13583"},
{"Thread":"Main","Number":"13584"},
{"Thread":"Main","Number":"13585"},
{"Thread":"Main","Number":"13586"},
{"Thread":"Main","Number":"13587"},
{"Thread":"Main","Number":"13588"},
{"Thread":"Main","Number":"13589"},
{"Thread":"Main","Number":"13590"},
{"Thread":"Main","Number":"13591"},
{"Thread":"Main","Number":"13592"},
{"Thread":"Main","Number":"13593"},
{"Thread":"Main","Number":"13594"},
{"Thread":"Main","Number":"13595"},
{"Thread":"Main","Number":"13596"},
{"Thread":"Main","Number":"13597"},
{"Thread":"Main","Number":"13598"},
{"Thread":"Main","Number":"13599"},
{"Thread":"Main","Number":"13600"},
{"Thread":"Main","Number":"13601"},
{"Thread":"Main","Number":"13602"},
{"Thread":"Main","Number":"13603"},
{"Thread":"Main","Number":"13604"},
{"Thread":"Main","Number":"13605"},
{"Thread":"Main","Number":"13606"},
{"Thread":"Main","Number":"13607"},
{"Thread":"Main","Number":"13608"},
{"Thread":"Main","Number":"13609"},
{"Thread":"Main","Number":"13610"},
{"Thread":"Main","Number":"13611"},
{"Thread":"Main","Number":"13612"},
{"Thread":"Main","Number":"13613"},
{"Thread":"Main","Number":"13614"},
{"Thread":"Main","Number":"13615"},
{"Thread":"Main","Number":"13616"},
{"Thread":"Main","Number":"13617"},
{"Thread":"Main","Number":"13618"},
{"Thread":"Main","Number":"13619"},
{"Thread":"Main","Number":"13620"},
{"Thread":"Main","Number":"13621"},
{"Thread":"Main","Number":"13622"},
{"Thread":"Main","Number":"13623"},
{"Thread":"Main","Number":"13624"},
{"Thread":"Main","Number":"13625"},
{"Thread":"Main","Number":"13626"},
{"Thread":"Main","Number":"13627"},
{"Thread":"Main","Number":"13628"},
{"Thread":"Main","Number":"13629"},
{"Thread":"Main","Number":"13630"},
{"Thread":"Main","Number":"13631"},
{"Thread":"Main","Number":"13632"},
{"Thread":"Main","Number":"13633"},
{"Thread":"Main","Number":"13634"},
{"Thread":"Main","Number":"13635"},
{"Thread":"Main","Number":"13636"},
{"Thread":"Main","Number":"13637"},
{"Thread":"Main","Number":"13638"},
{"Thread":"Main","Number":"13639"},
{"Thread":"Main","Number":"13640"},
{"Thread":"Main","Number":"13641"},
{"Thread":"Main","Number":"13642"},
{"Thread":"Main","Number":"13643"},
{"Thread":"Main","Number":"13644"},
{"Thread":"Main","Number":"13645"},
{"Thread":"Main","Number":"13646"},
{"Thread":"Main","Number":"13647"},
{"Thread":"Main","Number":"13648"},
{"Thread":"Main","Number":"13649"},
{"Thread":"Main","Number":"13650"},
{"Thread":"Main","Number":"13651"},
{"Thread":"Main","Number":"13652"},
{"Thread":"Main","Number":"13653"},
{"Thread":"Main","Number":"13654"},
{"Thread":"Main","Number":"13655"},
{"Thread":"Main","Number":"13656"},
{"Thread":"Main","Number":"13657"},
{"Thread":"Main","Number":"13658"},
{"Thread":"Main","Number":"13659"},
{"Thread":"Main","Number":"13660"},
{"Thread":"Main","Number":"13661"},
{"Thread":"Main","Number":"13662"},
{"Thread":"Main","Number":"13663"},
{"Thread":"Main","Number":"13664"},
{"Thread":"Main","Number":"13665"},
{"Thread":"Main","Number":"13666"},
{"Thread":"Main","Number":"13667"},
{"Thread":"Main","Number":"13668"},
{"Thread":"Main","Number":"13669"},
{"Thread":"Main","Number":"13670"},
{"Thread":"Main","Number":"13671"},
{"Thread":"Main","Number":"13672"},
{"Thread":"Main","Number":"13673"},
{"Thread":"Main","Number":"13674"},
{"Thread":"Main","Number":"13675"},
{"Thread":"Main","Number":"13676"},
{"Thread":"Main","Number":"13677"},
{"Thread":"Main","Number":"13678"},
{"Thread":"Main","Number":"13679"},
{"Thread":"Main","Number":"13680"},
{"Thread":"Main","Number":"13681"},
{"Thread":"Main","Number":"13682"},
{"Thread":"Main","Number":"13683"},
{"Thread":"Main","Number":"13684"},
{"Thread":"Main","Number":"13685"},
{"Thread":"Main","Number":"13686"},
{"Thread":"Main","Number":"13687"},
{"Thread":"Main","Number":"13688"},
{"Thread":"Main","Number":"13689"},
{"Thread":"Main","Number":"13690"},
{"Thread":"Main","Number":"13691"},
{"Thread":"Main","Number":"13692"},
{"Thread":"Main","Number":"13693"},
{"Thread":"Main","Number":"13694"},
{"Thread":"Main","Number":"13695"},
{"Thread":"Main","Number":"13696"},
{"Thread":"Main","Number":"13697"},
{"Thread":"Main","Number":"13698"},
{"Thread":"Main","Number":"13699"},
{"Thread":"Main","Number":"13700"},
{"Thread":"Main","Number":"13701"},
{"Thread":"Main","Number":"13702"},
{"Thread":"Main","Number":"13703"},
{"Thread":"Main","Number":"13704"},
{"Thread":"Main","Number":"13705"},
{"Thread":"Main","Number":"13706"},
{"Thread":"Main","Number":"13707"},
{"Thread":"Main","Number":"13708"},
{"Thread":"Main","Number":"13709"},
{"Thread":"Main","Number":"13710"},
{"Thread":"Main","Number":"13711"},
{"Thread":"Main","Number":"13712"},
{"Thread":"Main","Number":"13713"},
{"Thread":"Main","Number":"13714"},
{"Thread":"Main","Number":"13715"},
{"Thread":"Main","Number":"13716"},
{"Thread":"Main","Number":"13717"},
{"Thread":"Main","Number":"13718"},
{"Thread":"Main","Number":"13719"},
{"Thread":"Main","Number":"13720"},
{"Thread":"Main","Number":"13721"},
{"Thread":"Main","Number":"13722"},
{"Thread":"Main","Number":"13723"},
{"Thread":"Main","Number":"13724"},
{"Thread":"Main","Number":"13725"},
{"Thread":"Main","Number":"13726"},
{"Thread":"Main","Number":"13727"},
{"Thread":"Main","Number":"13728"},
{"Thread":"Main","Number":"13729"},
{"Thread":"Main","Number":"13730"},
{"Thread":"Main","Number":"13731"},
{"Thread":"Main","Number":"13732"},
{"Thread":"Main","Number":"13733"},
{"Thread":"Main","Number":"13734"},
{"Thread":"Main","Number":"13735"},
{"Thread":"Main","Number":"13736"},
{"Thread":"Main","Number":"13737"},
{"Thread":"Main","Number":"13738"},
{"Thread":"Main","Number":"13739"},
{"Thread":"Main","Number":"13740"},
{"Thread":"Main","Number":"13741"},
{"Thread":"Main","Number":"13742"},
{"Thread":"Main","Number":"13743"},
{"Thread":"Main","Number":"13744"},
{"Thread":"Main","Number":"13745"},
{"Thread":"Main","Number":"13746"},
{"Thread":"Main","Number":"13747"},
{"Thread":"Main","Number":"13748"},
{"Thread":"Main","Number":"13749"},
{"Thread":"Main","Number":"13750"},
{"Thread":"Main","Number":"13751"},
{"Thread":"Main","Number":"13752"},
{"Thread":"Main","Number":"13753"},
{"Thread":"Main","Number":"13754"},
{"Thread":"Main","Number":"13755"},
{"Thread":"Main","Number":"13756"},
{"Thread":"Main","Number":"13757"},
{"Thread":"Main","Number":"13758"},
{"Thread":"Main","Number":"13759"},
{"Thread":"Main","Number":"13760"},
{"Thread":"Main","Number":"13761"},
{"Thread":"Main","Number":"13762"},
{"Thread":"Main","Number":"13763"},
{"Thread":"Main","Number":"13764"},
{"Thread":"Main","Number":"13765"},
{"Thread":"Main","Number":"13766"},
{"Thread":"Main","Number":"13767"},
{"Thread":"Main","Number":"13768"},
{"Thread":"Main","Number":"13769"},
{"Thread":"Main","Number":"13770"},
{"Thread":"Main","Number":"13771"},
{"Thread":"Main","Number":"13772"},
{"Thread":"Main","Number":"13773"},
{"Thread":"Main","Number":"13774"},
{"Thread":"Main","Number":"13775"},
{"Thread":"Main","Number":"13776"},
{"Thread":"Main","Number":"13777"},
{"Thread":"Main","Number":"13778"},
{"Thread":"Main","Number":"13779"},
{"Thread":"Main","Number":"13780"},
{"Thread":"Main","Number":"13781"},
{"Thread":"Main","Number":"13782"},
{"Thread":"Main","Number":"13783"},
{"Thread":"Main","Number":"13784"},
{"Thread":"Main","Number":"13785"},
{"Thread":"Main","Number":"13786"},
{"Thread":"Main","Number":"13787"},
{"Thread":"Main","Number":"13788"},
{"Thread":"Main","Number":"13789"},
{"Thread":"Main","Number":"13790"},
{"Thread":"Main","Number":"13791"},
{"Thread":"Main","Number":"13792"},
{"Thread":"Main","Number":"13793"},
{"Thread":"Main","Number":"13794"},
{"Thread":"Main","Number":"13795"},
{"Thread":"Main","Number":"13796"},
{"Thread":"Main","Number":"13797"},
{"Thread":"Main","Number":"13798"},
{"Thread":"Main","Number":"13799"},
{"Thread":"Main","Number":"13800"},
{"Thread":"Main","Number":"13801"},
{"Thread":"Main","Number":"13802"},
{"Thread":"Main","Number":"13803"},
{"Thread":"Main","Number":"13804"},
{"Thread":"Main","Number":"13805"},
{"Thread":"Main","Number":"13806"},
{"Thread":"Main","Number":"13807"},
{"Thread":"Main","Number":"13808"},
{"Thread":"Main","Number":"13809"},
{"Thread":"Main","Number":"13810"},
{"Thread":"Main","Number":"13811"},
{"Thread":"Main","Number":"13812"},
{"Thread":"Main","Number":"13813"},
{"Thread":"Main","Number":"13814"},
{"Thread":"Main","Number":"13815"},
{"Thread":"Main","Number":"13816"},
{"Thread":"Main","Number":"13817"},
{"Thread":"Main","Number":"13818"},
{"Thread":"Main","Number":"13819"},
{"Thread":"Main","Number":"13820"},
{"Thread":"Main","Number":"13821"},
{"Thread":"Main","Number":"13822"},
{"Thread":"Main","Number":"13823"},
{"Thread":"Main","Number":"13824"},
{"Thread":"Main","Number":"13825"},
{"Thread":"Main","Number":"13826"},
{"Thread":"Main","Number":"13827"},
{"Thread":"Main","Number":"13828"},
{"Thread":"Main","Number":"13829"},
{"Thread":"Main","Number":"13830"},
{"Thread":"Main","Number":"13831"},
{"Thread":"Main","Number":"13832"},
{"Thread":"Main","Number":"13833"},
{"Thread":"Main","Number":"13834"},
{"Thread":"Main","Number":"13835"},
{"Thread":"Main","Number":"13836"},
{"Thread":"Main","Number":"13837"},
{"Thread":"Main","Number":"13838"},
{"Thread":"Main","Number":"13839"},
{"Thread":"Main","Number":"13840"},
{"Thread":"Main","Number":"13841"},
{"Thread":"Main","Number":"13842"},
{"Thread":"Main","Number":"13843"},
{"Thread":"Main","Number":"13844"},
{"Thread":"Main","Number":"13845"},
{"Thread":"Main","Number":"13846"},
{"Thread":"Main","Number":"13847"},
{"Thread":"Main","Number":"13848"},
{"Thread":"Main","Number":"13849"},
{"Thread":"Main","Number":"13850"},
{"Thread":"Main","Number":"13851"},
{"Thread":"Main","Number":"13852"},
{"Thread":"Main","Number":"13853"},
{"Thread":"Main","Number":"13854"},
{"Thread":"Main","Number":"13855"},
{"Thread":"Main","Number":"13856"},
{"Thread":"Main","Number":"13857"},
{"Thread":"Main","Number":"13858"},
{"Thread":"Main","Number":"13859"},
{"Thread":"Main","Number":"13860"},
{"Thread":"Main","Number":"13861"},
{"Thread":"Main","Number":"13862"},
{"Thread":"Main","Number":"13863"},
{"Thread":"Main","Number":"13864"},
{"Thread":"Main","Number":"13865"},
{"Thread":"Main","Number":"13866"},
{"Thread":"Main","Number":"13867"},
{"Thread":"Main","Number":"13868"},
{"Thread":"Main","Number":"13869"},
{"Thread":"Main","Number":"13870"},
{"Thread":"Main","Number":"13871"},
{"Thread":"Main","Number":"13872"},
{"Thread":"Main","Number":"13873"},
{"Thread":"Main","Number":"13874"},
{"Thread":"Main","Number":"13875"},
{"Thread":"Main","Number":"13876"},
{"Thread":"Main","Number":"13877"},
{"Thread":"Main","Number":"13878"},
{"Thread":"Main","Number":"13879"},
{"Thread":"Main","Number":"13880"},
{"Thread":"Main","Number":"13881"},
{"Thread":"Main","Number":"13882"},
{"Thread":"Main","Number":"13883"},
{"Thread":"Main","Number":"13884"},
{"Thread":"Main","Number":"13885"},
{"Thread":"Main","Number":"13886"},
{"Thread":"Main","Number":"13887"},
{"Thread":"Main","Number":"13888"},
{"Thread":"Main","Number":"13889"},
{"Thread":"Main","Number":"13890"},
{"Thread":"Main","Number":"13891"},
{"Thread":"Main","Number":"13892"},
{"Thread":"Main","Number":"13893"},
{"Thread":"Main","Number":"13894"},
{"Thread":"Main","Number":"13895"},
{"Thread":"Main","Number":"13896"},
{"Thread":"Main","Number":"13897"},
{"Thread":"Main","Number":"13898"},
{"Thread":"Main","Number":"13899"},
{"Thread":"Main","Number":"13900"},
{"Thread":"Main","Number":"13901"},
{"Thread":"Main","Number":"13902"},
{"Thread":"Main","Number":"13903"},
{"Thread":"Main","Number":"13904"},
{"Thread":"Main","Number":"13905"},
{"Thread":"Main","Number":"13906"},
{"Thread":"Main","Number":"13907"},
{"Thread":"Main","Number":"13908"},
{"Thread":"Main","Number":"13909"},
{"Thread":"Main","Number":"13910"},
{"Thread":"Main","Number":"13911"},
{"Thread":"Main","Number":"13912"},
{"Thread":"Main","Number":"13913"},
{"Thread":"Main","Number":"13914"},
{"Thread":"Main","Number":"13915"},
{"Thread":"Main","Number":"13916"},
{"Thread":"Main","Number":"13917"},
{"Thread":"Main","Number":"13918"},
{"Thread":"Main","Number":"13919"},
{"Thread":"Main","Number":"13920"},
{"Thread":"Main","Number":"13921"},
{"Thread":"Main","Number":"13922"},
{"Thread":"Main","Number":"13923"},
{"Thread":"Main","Number":"13924"},
{"Thread":"Main","Number":"13925"},
{"Thread":"Main","Number":"13926"},
{"Thread":"Main","Number":"13927"},
{"Thread":"Main","Number":"13928"},
{"Thread":"Main","Number":"13929"},
{"Thread":"Main","Number":"13930"},
{"Thread":"Main","Number":"13931"},
{"Thread":"Main","Number":"13932"},
{"Thread":"Main","Number":"13933"},
{"Thread":"Main","Number":"13934"},
{"Thread":"Main","Number":"13935"},
{"Thread":"Main","Number":"13936"},
{"Thread":"Main","Number":"13937"},
{"Thread":"Main","Number":"13938"},
{"Thread":"Main","Number":"13939"},
{"Thread":"Main","Number":"13940"},
{"Thread":"Main","Number":"13941"},
{"Thread":"Main","Number":"13942"},
{"Thread":"Main","Number":"13943"},
{"Thread":"Main","Number":"13944"},
{"Thread":"Main","Number":"13945"},
{"Thread":"Main","Number":"13946"},
{"Thread":"Main","Number":"13947"},
{"Thread":"Main","Number":"13948"},
{"Thread":"Main","Number":"13949"},
{"Thread":"Main","Number":"13950"},
{"Thread":"Main","Number":"13951"},
{"Thread":"Main","Number":"13952"},
{"Thread":"Main","Number":"13953"},
{"Thread":"Main","Number":"13954"},
{"Thread":"Main","Number":"13955"},
{"Thread":"Main","Number":"13956"},
{"Thread":"Main","Number":"13957"},
{"Thread":"Main","Number":"13958"},
{"Thread":"Main","Number":"13959"},
{"Thread":"Main","Number":"13960"},
{"Thread":"Main","Number":"13961"},
{"Thread":"Main","Number":"13962"},
{"Thread":"Main","Number":"13963"},
{"Thread":"Main","Number":"13964"},
{"Thread":"Main","Number":"13965"},
{"Thread":"Main","Number":"13966"},
{"Thread":"Main","Number":"13967"},
{"Thread":"Main","Number":"13968"},
{"Thread":"Main","Number":"13969"},
{"Thread":"Main","Number":"13970"},
{"Thread":"Main","Number":"13971"},
{"Thread":"Main","Number":"13972"},
{"Thread":"Main","Number":"13973"},
{"Thread":"Main","Number":"13974"},
{"Thread":"Main","Number":"13975"},
{"Thread":"Main","Number":"13976"},
{"Thread":"Main","Number":"13977"},
{"Thread":"Main","Number":"13978"},
{"Thread":"Main","Number":"13979"},
{"Thread":"Main","Number":"13980"},
{"Thread":"Main","Number":"13981"},
{"Thread":"Main","Number":"13982"},
{"Thread":"Main","Number":"13983"},
{"Thread":"Main","Number":"13984"},
{"Thread":"Main","Number":"13985"},
{"Thread":"Main","Number":"13986"},
{"Thread":"Main","Number":"13987"},
{"Thread":"Main","Number":"13988"},
{"Thread":"Main","Number":"13989"},
{"Thread":"Main","Number":"13990"},
{"Thread":"Main","Number":"13991"},
{"Thread":"Main","Number":"13992"},
{"Thread":"Main","Number":"13993"},
{"Thread":"Main","Number":"13994"},
{"Thread":"Main","Number":"13995"},
{"Thread":"Main","Number":"13996"},
{"Thread":"Main","Number":"13997"},
{"Thread":"Main","Number":"13998"},
{"Thread":"Main","Number":"13999"},
{"Thread":"Main","Number":"14000"}]